pykriweather/pykriweather.py
pykriweather-0.0.1.dist-info/LICENSE
pykriweather-0.0.1.dist-info/METADATA
pykriweather-0.0.1.dist-info/WHEEL
pykriweather-0.0.1.dist-info/top_level.txt
pykriweather-0.0.1.dist-info/RECORD
