Metadata-Version: 2.1
Name: pykriweather
Version: 0.0.1
Summary: Python Distribution Utilities
Home-page: https://github.com/pykrishna/pykriweather.git
Author: Krishna Mishra
Author-email: krishna1994.m@gmail.com
License: MIT
Platform: UNKNOWN
Requires-Dist: pyowm
